enchaintesdk/__init__.py
enchaintesdk/enchainte_client.py
enchaintesdk/anchor/__init__.py
enchaintesdk/anchor/entity/__init__.py
enchaintesdk/anchor/entity/anchor_entity.py
enchaintesdk/anchor/entity/network_entity.py
enchaintesdk/anchor/repository/__init__.py
enchaintesdk/anchor/repository/anchor_repository.py
enchaintesdk/anchor/service/__init__.py
enchaintesdk/anchor/service/anchor_service.py
enchaintesdk/config/__init__.py
enchaintesdk/config/entity/__init__.py
enchaintesdk/config/entity/config_env_entity.py
enchaintesdk/config/entity/configuration_entity.py
enchaintesdk/config/repository/__init__.py
enchaintesdk/config/repository/config_data.py
enchaintesdk/config/repository/config_repository.py
enchaintesdk/config/service/__init__.py
enchaintesdk/config/service/config_service.py
enchaintesdk/exceptions/__init__.py
enchaintesdk/infrastructure/__init__.py
enchaintesdk/infrastructure/blockchain/__init__.py
enchaintesdk/infrastructure/blockchain/web3.py
enchaintesdk/infrastructure/blockchain/web3_exception.py
enchaintesdk/infrastructure/hashing/__init__.py
enchaintesdk/infrastructure/hashing/blake2b.py
enchaintesdk/infrastructure/hashing/keccak.py
enchaintesdk/infrastructure/http/__init__.py
enchaintesdk/infrastructure/http/http_client.py
enchaintesdk/infrastructure/http/http_data.py
enchaintesdk/infrastructure/http/http_exception.py
enchaintesdk/infrastructure/http/dto/__init__.py
enchaintesdk/infrastructure/http/dto/api_response_entity.py
enchaintesdk/message/__init__.py
enchaintesdk/message/entity/__init__.py
enchaintesdk/message/entity/message_entity.py
enchaintesdk/message/entity/message_receipt_entity.py
enchaintesdk/message/entity/dto/__init__.py
enchaintesdk/message/entity/dto/message_write_response_entity.py
enchaintesdk/message/entity/exception/__init__.py
enchaintesdk/message/entity/exception/invalid_message_exception.py
enchaintesdk/message/repository/__init__.py
enchaintesdk/message/repository/message_repository.py
enchaintesdk-0.1.3.dist-info/LICENSE
enchaintesdk-0.1.3.dist-info/METADATA
enchaintesdk-0.1.3.dist-info/WHEEL
enchaintesdk-0.1.3.dist-info/top_level.txt
enchaintesdk-0.1.3.dist-info/RECORD
