Metadata-Version: 2.1
Name: enchaintesdk
Version: 0.1.3
Summary: Enchainté SDK for Python3
Home-page: https://github.com/enchainte/enchainte-sdk-py
Author: Albert Canyelles Ruiz
Author-email: acanyelles@enchainte.com
License: UNKNOWN
Platform: UNKNOWN
Classifier: Programming Language :: Python :: 3
Classifier: License :: OSI Approved :: MIT License
Classifier: Operating System :: OS Independent
Requires-Python: >=3.5
License-File: LICENSE
Requires-Dist: requests (>=2.24.0)
Requires-Dist: web3 (>=5.6.0)
Requires-Dist: pycryptodome (>=3.0)
